<?xml version="1.0" encoding="utf-8"?>
<odoo>
    <record id="view_order_product_tree_inherit_pos_status" model="ir.ui.view">
        <field name="name">sale.report.tree.inherit.pos.status</field>
        <field name="model">sale.report</field>
        <field name="inherit_id" ref="sale.sale_report_view_tree"/>        
        <field name="arch" type="xml">

            <xpath expr="//field[@name='invoice_status']" position="attributes">
                <attribute name="invisible">1</attribute>
            </xpath>

            <xpath expr="//field[@name='invoice_status']" position="after">
                <field name="invoice_status_computed"/>
            </xpath>
        </field>
    </record>
</odoo>